emailmessaging/__init__.py
emailmessaging/emailmessage.py
emailmessaging-1.0.dist-info/DESCRIPTION.rst
emailmessaging-1.0.dist-info/METADATA
emailmessaging-1.0.dist-info/RECORD
emailmessaging-1.0.dist-info/WHEEL
emailmessaging-1.0.dist-info/metadata.json
emailmessaging-1.0.dist-info/top_level.txt
