Metadata-Version: 2.0
Name: emailmessaging
Version: 1.0
Summary: Simple email sender
Home-page: UNKNOWN
Author: Simon
Author-email: simon.stoiljkovikj@gmail.com
License: UNKNOWN
Platform: UNKNOWN
Requires-Dist: envelopes
